Metadata-Version: 2.1
Name: django-custom-fieldsets
Version: 0.0.1
Summary: Custom fieldset settings for django admin
Author: Sidq
Author-email: abba.dmytro@gmail.com
License:                                  Apache License
Project-URL: GitHub, https://github.com/sidqdev/django-custom-fieldsets
Project-URL: Telegram, https://t.me/sidqdev
Classifier: Programming Language :: Python :: 3
Classifier: Operating System :: OS Independent
Requires: django
Requires-Python: >=3.6
License-File: LICENSE
